{
  "fill-specializations" : [
    {
      "value" : {
        "automatic-gradient" : "display-p3:0.96196,0.91881,0.96783,1.00000"
      }
    },
    {
      "appearance" : "dark",
      "value" : {
        "automatic-gradient" : "display-p3:0.08914,0.03251,0.04798,1.00000"
      }
    }
  ],
  "groups" : [
    {
      "layers" : [
        {
          "glass" : false,
          "image-name" : "S.svg",
          "name" : "S",
          "position" : {
            "scale" : 0.64,
            "translation-in-points" : [
              0,
              11.621716520123073
            ]
          }
        }
      ],
      "shadow" : {
        "kind" : "neutral",
        "opacity" : 0.5
      },
      "translucency" : {
        "enabled" : false,
        "value" : 0.5
      }
    }
  ],
  "supported-platforms" : {
    "circles" : [
      "watchOS"
    ],
    "squares" : "shared"
  }
}